crl.devutils-1.4.0-py3.10-nspkg.pth
crl/devutils/__init__.py
crl/devutils/_tmpindex.py
crl/devutils/_version.py
crl/devutils/changehandler.py
crl/devutils/devpihandler.py
crl/devutils/devpiindex.py
crl/devutils/doccreator.py
crl/devutils/githandler.py
crl/devutils/packagehandler.py
crl/devutils/runner.py
crl/devutils/setuphandler.py
crl/devutils/tasks.py
crl/devutils/tmpdir.py
crl/devutils/utils.py
crl/devutils/versionhandler.py
crl.devutils-1.4.0.dist-info/LICENSE
crl.devutils-1.4.0.dist-info/METADATA
crl.devutils-1.4.0.dist-info/WHEEL
crl.devutils-1.4.0.dist-info/entry_points.txt
crl.devutils-1.4.0.dist-info/namespace_packages.txt
crl.devutils-1.4.0.dist-info/top_level.txt
crl.devutils-1.4.0.dist-info/RECORD
