Metadata-Version: 2.1
Name: crl.devutils
Version: 1.4.0
Summary: Common Robot Libraries development and CI tools
Home-page: https://github.com/nokia/crl-devutils
Author: Petri Huovinen
Author-email: petri.huovinen@nokia.com
License: BSD 3-Clause
Keywords: robotframework testing testautomation acceptancetesting atdd bdd
Classifier: Intended Audience :: Developers
Classifier: License :: OSI Approved :: BSD License
Classifier: Programming Language :: Python :: 2
Classifier: Programming Language :: Python :: 2.7
Classifier: Programming Language :: Python :: 3
Classifier: Programming Language :: Python :: 3.5
Classifier: Programming Language :: Python :: 3.6
Classifier: Programming Language :: Python :: 3.7
Classifier: Programming Language :: Python :: 3.8
Classifier: Programming Language :: Python :: 3.9
Classifier: Programming Language :: Python :: 3.10
Classifier: Topic :: Software Development
License-File: LICENSE
Requires-Dist: invoke==0.12.2
Requires-Dist: check-manifest==0.41
Requires-Dist: devpi-client==5.2.3
Requires-Dist: tox==3.24.5
Requires-Dist: future
Requires-Dist: six
Requires-Dist: rstcheck
Requires-Dist: sphinx<7.0
Requires-Dist: robotframework
Requires-Dist: virtualenvrunner
Requires-Dist: virtualenv==20.13.4
Requires-Dist: configparser
Requires-Dist: Jinja2==3.0.3; python_version > "3.0"
Requires-Dist: setuptools==68.2.2; python_version >= "3.10"
